civic_lib_core/__init__.py
civic_lib_core/_version.py
civic_lib_core/config_utils.py
civic_lib_core/date_utils.py
civic_lib_core/dev_utils.py
civic_lib_core/fs_utils.py
civic_lib_core/graphql_utils.py
civic_lib_core/log_utils.py
civic_lib_core/path_utils.py
civic_lib_core/policy_utils.py
civic_lib_core/project_checks.py
civic_lib_core/project_layout.py
civic_lib_core/project_policy.py
civic_lib_core/project_policy.yaml
civic_lib_core/py.typed
civic_lib_core/report_archiver.py
civic_lib_core/report_constants.py
civic_lib_core/report_formatter.py
civic_lib_core/report_indexer.py
civic_lib_core/report_reader.py
civic_lib_core/report_summary.py
civic_lib_core/report_utils.py
civic_lib_core/report_writer.py
civic_lib_core/schema_utils.py
civic_lib_core/version_utils.py
civic_lib_core/yaml_utils.py
civic_lib_core/cli/__init__.py
civic_lib_core/cli/__main__.py
civic_lib_core/cli/build_api.py
civic_lib_core/cli/bump_version.py
civic_lib_core/cli/check_policy.py
civic_lib_core/cli/cli.py
civic_lib_core/cli/layout.py
civic_lib_core/cli/prep_code.py
civic_lib_core/cli/release.py
civic_lib_core-0.9.14.dist-info/licenses/LICENSE
civic_lib_core-0.9.14.dist-info/METADATA
civic_lib_core-0.9.14.dist-info/WHEEL
civic_lib_core-0.9.14.dist-info/entry_points.txt
civic_lib_core-0.9.14.dist-info/top_level.txt
civic_lib_core-0.9.14.dist-info/RECORD
